{
  "id": 4770,
  "metadata": {
    "volume": {
      "id": 5
    },
    "chapter": {
      "id": 46,
      "language": {
        "en": {
          "text": "The Book of Oaths (qasamah), Retaliation and Blood Money"
        },
        "ar": {
          "text": "كتاب القسامة"
        },
        "ur": {
          "text": "قسامہ ، قصاص اور دیت کے احکام و مسائل"
        },
        "al": {
          "text": ""
        }
      }
    }
  },
  "language": {
    "ar": {
      "text": "أَخْبَرَنَا عَبْدُ الْجَبَّارِ بْنُ الْعَلَاءِ بْنِ عَبْدِ الْجَبَّارِ، ‏‏‏‏‏‏عَنْ سُفْيَانَ، ‏‏‏‏‏‏عَنْ عَمْرٍو، ‏‏‏‏‏‏عَنْ عَطَاءٍ، ‏‏‏‏‏‏عَنْ صَفْوَانَ بْنِ يَعْلَى، ‏‏‏‏‏‏عَنْ أَبِيهِ:‏‏‏‏ أَنَّ رَجُلًا عَضَّ يَدَ رَجُلٍ،‏‏‏‏ فَانْتُزِعَتْ ثَنِيَّتُهُ، ‏‏‏‏‏‏فَأَتَى النَّبِيَّ صَلَّى اللَّهُ عَلَيْهِ وَسَلَّمَ فَأَهْدَرَهَا ."
    },
    "en": {
      "narrator": "",
      "text": "It was narrated from Safwan bin Ya'la, from his father, that: a man bit the hand of another man and his front tooth fell out. He came to the Prophet but he considered it in vain."
    },
    "ur": {
      "narrator": "یعلیٰ رضی اللہ عنہ سے روایت ہے کہ",
      "text": "ایک شخص نے دوسرے شخص کا ہاتھ کاٹ کھایا تو پہلے شخص کا دانت اکھڑ گیا، وہ نبی اکرم صلی اللہ علیہ وسلم کے پاس آیا، تو آپ نے اسے لغو قرار دیا ۱؎۔"
    },
    "al": {
      "text": ""
    }
  }
}