{
  "id": 6372,
  "metadata": {
    "volume": {
      "id": 6
    },
    "chapter": {
      "id": 45,
      "language": {
        "en": {
          "text": "The Book of the Merits of the Companions"
        },
        "ar": {
          "text": "كتاب فَضَائِلِ الصَّحَابَةِ"
        },
        "ur": {
          "text": "صحابہ کرام رضی اللہ عنھم کے فضائل و مناقب"
        },
        "al": {
          "text": ""
        }
      }
    }
  },
  "language": {
    "ar": {
      "text": "حَدَّثَنَا مُحَمَّدُ بْنُ الْمُثَنَّى، وَابْنُ بَشَّارٍ، قَالَا: حَدَّثَنَا مُحَمَّدُ بْنُ جَعْفَرٍ، حَدَّثَنَا شُعْبَةُ، سَمِعْتُ قَتَادَةَ، يُحَدِّثُ عَنْ أَنَسٍ، عَنْ أُمِّ سُلَيْمٍ، أَنَّهَا قَالَتْ: يَا رَسُولَ اللهِ خَادِمُكَ أَنَسٌ، ادْعُ اللهَ لَهُ، فَقَالَ: «اللهُمَّ أَكْثِرْ مَالَهُ وَوَلَدَهُ، وَبَارِكْ لَهُ فِيمَا أَعْطَيْتَهُ»."
    },
    "en": {
      "narrator": "Anas رضی اللہ عنہ reported that Umm Sulaim رضی اللہ عنہا said:",
      "text": "Allah's Messenger ﷺ, here is your servant Anas رضی اللہ عنہ , invoke blessings of Allah upon him. Thereupon he (the Holy Prophet ﷺ) said: O Allah, make an increase in his wealth, and progeny, and confer blessings upon him in everything Thou hast bestowed upon him."
    },
    "ur": {
      "narrator": "ہم سے محمد بن المثنی اور ابن بشار نے بیان کیا، کہا: محمد بن جعفر نے کہا : ہمیں شعبہ نے حدیث سنائی ، انھوں نے کہا : میں نے قتادہ سے سنا ، وہ حضرت انس رضی اللہ عنہ سے حدیث بیان کررہے تھے ، انھوں نے حضرت ام سلیم رضی اللہ عنہا سے روایت کی ، انھوں نے کہا",
      "text": "اللہ کے رسول اللہ صلی اللہ علیہ وسلم !انس آپ کا خادم ہے آپ اس کے لیے اللہ سے دعا کیجئے تو آپ نے کہا : \" اے اللہ !اس کے مال اور اولاد کو زیادہ کر اور اس کو جو کچھ تو نے عطا کیا ہے ، اس میں برکت عطافر ما ! \""
    },
    "al": {
      "text": ""
    }
  }
}