{
  "id": 4546,
  "metadata": {
    "volume": {
      "id": 65
    },
    "chapter": {
      "id": 1,
      "language": {
        "en": {
          "text": "Chapter 1"
        },
        "ar": {
          "text": "باب"
        },
        "al": {
          "text": ""
        }
      }
    }
  },
  "language": {
    "ar": {
      "text": "حَدَّثَنَا إِبْرَاهِيمُ بْنُ مُوسَى، حَدَّثَنَا هِشَامٌ، أَنَّ ابْنَ جُرَيْجٍ، أَخْبَرَهُمْ قَالَ ابْنُ أَبِي مُلَيْكَةَ سَمِعْتُ عَائِشَةَ، تَقْرَأُ ‏{‏إِذْ تَلِقُونَهُ بِأَلْسِنَتِكُمْ‏}‏"
    },
    "al": {
      "text": "Transmeton Ajsheja: \"Kur ju e shpiknit gënjeshtrën (dhe e bartnit) me gjuhët tuaja.\" (24:15)"
    },
    "en": {
      "narrator": "Narrated Ibn Abi Mulaika:",
      "text": "I heard `Aisha reciting: \"When you invented a lie (and carry it) on your tongues.\" (24.15)"
    }
  }
}