{
  "id": 4581,
  "metadata": {
    "volume": {
      "id": 65
    },
    "chapter": {
      "id": 1,
      "language": {
        "en": {
          "text": "Chapter 1"
        },
        "ar": {
          "text": "باب"
        },
        "al": {
          "text": ""
        }
      }
    }
  },
  "language": {
    "ar": {
      "text": "حَدَّثَنَا مُحَمَّدُ بْنُ عَبْدِ الرَّحِيمِ، حَدَّثَنَا مُعَلَّى بْنُ مَنْصُورٍ، عَنْ حَمَّادِ بْنِ زَيْدٍ، حَدَّثَنَا ثَابِتٌ، عَنْ أَنَسِ بْنِ مَالِكٍ ـ رضى الله عنه ـ أَنَّ هَذِهِ، الآيَةَ ‏{‏وَتُخْفِي فِي نَفْسِكَ مَا اللَّهُ مُبْدِيهِ‏}‏ نَزَلَتْ فِي شَأْنِ زَيْنَبَ ابْنَةِ جَحْشٍ وَزَيْدِ بْنِ حَارِثَةَ‏.‏"
    },
    "al": {
      "text": "Transmeton Enes bin Maliku: Ajeti: \"Dhe ti e fshehe në veten tënde atë që Allahu do ta shfaqte\" (33:37), u shpall lidhur me Zejnebe bint Xhahshin dhe Zejd bin Harithen."
    },
    "en": {
      "narrator": "Narrated Anas bin Malik:",
      "text": "The Verse: 'But you did hide in your mind that which Allah was about to make manifest.' (33.37) was revealed concerning Zainab bint Jahsh and Zaid bin Haritha."
    }
  }
}