{
  "id": 2666,
  "metadata": {
    "volume": {
      "id": 3
    },
    "chapter": {
      "id": 15,
      "language": {
        "en": {
          "text": "Jihad (Kitab Al-Jihad)"
        },
        "ar": {
          "text": "كتاب الجهاد"
        },
        "ur": {
          "text": "جہاد کے مسائل"
        },
        "al": {
          "text": ""
        }
      }
    }
  },
  "language": {
    "ar": {
      "text": "حَدَّثَنَا مُحَمَّدُ بْنُ عِيسَى، ‏‏‏‏‏‏وَزِيَادُ بْنُ أَيُّوبَ، ‏‏‏‏‏‏قَالَا:‏‏‏‏ حَدَّثَنَا هُشَيْمٌ، ‏‏‏‏‏‏أَخْبَرَنَا مُغِيرَةُ، ‏‏‏‏‏‏عَنْ شِبَاكٍ، ‏‏‏‏‏‏عَنْ إِبْرَاهِيمَ، ‏‏‏‏‏‏عَنْ هُنَيِّ بْنِ نُوَيْرَةَ، ‏‏‏‏‏‏عَنْ عَلْقَمَةَ، ‏‏‏‏‏‏عَنْ عَبْدِ اللَّهِ، ‏‏‏‏‏‏قَالَ:‏‏‏‏ قَالَ رَسُولُ اللَّهِ صَلَّى اللَّهُ عَلَيْهِ وَسَلَّمَ:‏‏‏‏ أَعَفُّ النَّاسِ قِتْلَةً أَهْلُ الْإِيمَانِ ."
    },
    "en": {
      "narrator": "Narrated Abdullah Ibn Masud رضی اللہ عنہ :",
      "text": "The Prophet صلی ‌اللہ ‌علیہ ‌وسلم said: The most merciful of the people in respect of killing are believers (in Allah)."
    },
    "ur": {
      "narrator": "ہم سے محمد بن عیسیٰ اور زیاد بن ایوب نے بیان کیا، کہا کہ ہم سے ہشام نے بیان کیا، کہا: ہم کو مغیرہ نے شیباک کی سند سے، ابراہیم کی سند سے، حنیہ بن نویرہ کی سند سے، علقمہ سے, عبداللہ بن مسعود رضی اللہ عنہ کہتے ہیں کہ",
      "text": "رسول اللہ صلی اللہ علیہ وسلم نے فرمایا: لوگوں میں سب سے بہتر قتل کرنے والے صاحب ایمان لوگ ہیں ۔"
    },
    "al": {
      "text": ""
    }
  }
}