{
  "id": 4824,
  "metadata": {
    "volume": {
      "id": 5
    },
    "chapter": {
      "id": 34,
      "language": {
        "en": {
          "text": "The Book of Government"
        },
        "ar": {
          "text": "كتاب الْإِمَارَةِ"
        },
        "ur": {
          "text": "امور حکومت کا بیان"
        },
        "al": {
          "text": ""
        }
      }
    }
  },
  "language": {
    "ar": {
      "text": "وحَدَّثَنَا إِسْحَاقُ بْنُ إِبْرَاهِيمَ، أَخْبَرَنَا الْمَخْزُومِيُّ، حَدَّثَنَا وُهَيْبٌ، حَدَّثَنَا عَمْرُو بْنُ يَحْيَى، عَنْ عَبَّادِ بْنِ تَمِيمٍ، عَنْ عَبْدِ اللهِ بْنِ زَيْدٍ، قَالَ: أَتَاهُ آتٍ، فَقَالَ: هَا ذَاكَ ابْنُ حَنْظَلَةَ يُبَايِعُ النَّاسَ، فَقَالَ: عَلَى مَاذَا؟ قَالَ: عَلَى الْمَوْتِ، قَالَ: «لَا أُبَايِعُ عَلَى هَذَا أَحَدًا بَعْدَ رَسُولِ اللهِ صَلَّى اللهُ عَلَيْهِ وَسَلَّمَ»."
    },
    "en": {
      "narrator": "It has been narrated on the authority of Abdullah bin Zaid رضی اللہ عنہ who said:",
      "text": "A person came to him and said: Here is Ibn Hanzala who is making people swear allegiance to him. He (, Abdullah) asked: To what effect? He replied: To the effect that they will die for him. 'Abdullah said: I will never swear allegiance to this effect after the Messenger of Allah ( ‌صلی ‌اللہ ‌علیہ ‌وسلم ‌)."
    },
    "ur": {
      "narrator": "ہم سے اسحاق بن ابراہیم نے بیان کیا، کہا ہم سے المخزومی نے بیان کیا، کہا ہم سے وہیب نے بیان کیا، ہم سے عمرو بن یحییٰ نے بیان کیا, عباد بن تمیم نے حضرت عبداللہ بن زید رضی اللہ عنہ سے روایت کی ، کہا",
      "text": "ان کے پاس کوئی شخص آیا اور کہنے لگا : ابن حنظلہ لوگوں سے بیعت لے رہے ہیں؟ پوچھا : کس چیز پر؟ کہا : موت پر ۔ کہا : میں رسول اللہ صلی اللہ علیہ وسلم کے بعد کسی شخص کے ساتھ اس بات پر بیعت نہیں کروں گا ۔"
    },
    "al": {
      "text": ""
    }
  }
}