{
  "id": 5458,
  "metadata": {
    "volume": {
      "id": 75
    },
    "chapter": {
      "id": 19,
      "language": {
        "en": {
          "text": "The patient's wish for death"
        },
        "ar": {
          "text": "باب تَمَنِّي الْمَرِيضِ الْمَوْتَ"
        },
        "al": {
          "text": ""
        }
      }
    }
  },
  "language": {
    "ar": {
      "text": "حَدَّثَنَا آدَمُ، حَدَّثَنَا شُعْبَةُ، عَنْ إِسْمَاعِيلَ بْنِ أَبِي خَالِدٍ، عَنْ قَيْسِ بْنِ أَبِي حَازِمٍ، قَالَ دَخَلْنَا عَلَى خَبَّابٍ نَعُودُهُ وَقَدِ اكْتَوَى سَبْعَ كَيَّاتٍ فَقَالَ إِنَّ أَصْحَابَنَا الَّذِينَ سَلَفُوا مَضَوْا وَلَمْ تَنْقُصْهُمُ الدُّنْيَا وَإِنَّا أَصَبْنَا مَا لاَ نَجِدُ لَهُ مَوْضِعًا إِلاَّ التُّرَابَ وَلَوْلاَ أَنَّ النَّبِيَّ صلى الله عليه وسلم نَهَانَا أَنْ نَدْعُوَ بِالْمَوْتِ لَدَعَوْتُ بِهِ، ثُمَّ أَتَيْنَاهُ مَرَّةً أُخْرَى وَهْوَ يَبْنِي حَائِطًا لَهُ فَقَالَ إِنَّ الْمُسْلِمَ لَيُوجَرُ فِي كُلِّ شَىْءٍ يُنْفِقُهُ إِلاَّ فِي شَىْءٍ يَجْعَلُهُ فِي هَذَا التُّرَابِ‏.‏"
    },
    "al": {
      "text": "Transmeton Kajs bin Ebi Hazimi: Shkuam për ta vizituar Hababin, i cili ishte i sëmurë, dhe ai ishte mjekuar me djegie (kauterizim) në shtatë vende të trupit të tij. Ai tha: \"Shokët tanë që kaluan para nesh, u larguan nga kjo botë pa u pakësuar shpërblimi i tyre (përmes kënaqësive të kësaj jete), ndërsa ne kemi fituar aq shumë pasuri, saqë nuk gjejmë vend tjetër për ta shpenzuar përveçse në dhé (ndërtim). Sikur Pejgamberi (s.a.v.s.) të mos na kishte ndaluar që të kërkonim vdekjen, unë do ta kisha kërkuar atë.\" Më vonë e vizituam përsëri kur ai po ndërtonte një mur dhe tha: \"Muslimani shpërblehet për çdo gjë që shpenzon, përveç asaj që shpenzon në këtë dhé (ndërtim).\""
    },
    "en": {
      "narrator": "Narrated Qais bin Abi Hazim:",
      "text": "We went to pay a visit to Khabbab (who was sick) and he had been branded (cauterized) at seven places in his body. He said, \"Our companions who died (during the lifetime of the Prophet) left (this world) without having their rewards reduced through enjoying the pleasures of this life, but we have got (so much) wealth that we find no way to spend It except on the construction of buildings Had the Prophet not forbidden us to wish for death, I would have wished for it.' We visited him for the second time while he was building a wall. He said, A Muslim is rewarded (in the Hereafter) for whatever he spends except for something that he spends on building.\""
    }
  }
}