{
  "id": 1722,
  "metadata": {
    "volume": {
      "id": 2
    },
    "chapter": {
      "id": 6,
      "language": {
        "en": {
          "text": "The Book of Prayer - Travellers"
        },
        "ar": {
          "text": "كتاب صَلَاةِ الْمُسَافِرِينَ وَقَصْرِهَا"
        },
        "ur": {
          "text": "مسافرو ں کی نماز قصر کا بیان"
        },
        "al": {
          "text": ""
        }
      }
    }
  },
  "language": {
    "ar": {
      "text": "و حَدَّثَنَا قُتَيْبَةُ بْنُ سَعِيدٍ حَدَّثَنَا لَيْثٌ عَنْ يَزِيدَ بْنِ أَبِي حَبِيبٍ عَنْ عِرَاكِ بْنِ مَالِكٍ عَنْ عُرْوَةَ أَنَّ عَائِشَةَ أَخْبَرَتْهُ أَنَّ رَسُولَ اللَّهِ صَلَّى اللَّهُ عَلَيْهِ وَسَلَّمَ كَانَ يُصَلِّي ثَلَاثَ عَشْرَةَ رَكْعَةً بِرَكْعَتَيْ الْفَجْرِ."
    },
    "en": {
      "narrator": "A'isha رضی اللہ عنہا reported:",
      "text": "The Messenger of Allah ( ‌صلی ‌اللہ ‌علیہ ‌وسلم ‌) used to pray thirteen rak'ahs during the night including the two rak'ahs (Sunan) of the dawn prayer."
    },
    "ur": {
      "narrator": "ہم سے قتیبہ بن سعید نے بیان کیا، کہا ہم سے لیث نے بیان کیا، ان سے یزید بن ابی حبیب نے بیان کیا، ان سے عرق بن مالک رضی اللہ عنہ نے,عروہ بن مالک نے عروہ سے روایت کی کہ حضرت عائشہ رضی اللہ عنہا نے انھیں بتایا کہ",
      "text": "رسول اللہ صلی اللہ علیہ وسلم فجر کی دو رکعتوں سمیت تیرہ ر کعتیں پڑھا کرتے تھے ۔"
    },
    "al": {
      "text": ""
    }
  }
}