{
  "id": 789,
  "metadata": {
    "volume": {
      "id": 1
    },
    "chapter": {
      "id": 2,
      "language": {
        "en": {
          "text": "Prayer (Kitab Al-Salat)"
        },
        "ar": {
          "text": "كتاب الصلاة"
        },
        "ur": {
          "text": "نماز کے احکام و مسائل"
        },
        "al": {
          "text": ""
        }
      }
    }
  },
  "language": {
    "ar": {
      "text": "حَدَّثَنَا عَبْدُ الرَّحْمَنِ بْنُ إِبْرَاهِيمَ، ‏‏‏‏‏‏حَدَّثَنَا عُمَرُ بْنُ عَبْدِ الْوَاحِدِ، ‏‏‏‏‏‏وَبِشْرُ بْنُ بَكْرٍ، ‏‏‏‏‏‏عَنْ الْأَوْزَاعِيِّ، ‏‏‏‏‏‏عَنْ يَحْيَى بْنِ أَبِي كَثِيرٍ، ‏‏‏‏‏‏عَنْ عَبْدِ اللَّهِ بْنِ أَبِي قَتَادَةَ، ‏‏‏‏‏‏عَنْ أَبِيهِ، ‏‏‏‏‏‏قَالَ:‏‏‏‏ قَالَ رَسُولُ اللَّهِ صَلَّى اللَّهُ عَلَيْهِ وَسَلَّمَ:‏‏‏‏ إِنِّي لَأَقُومُ إِلَى الصَّلَاةِ وَأَنَا أُرِيدُ أَنْ أُطَوِّلَ فِيهَا، ‏‏‏‏‏‏فَأَسْمَعُ بُكَاءَ الصَّبِيِّ فَأَتَجَوَّزُ كَرَاهِيَةَ أَنْ أَشُقَّ عَلَى أُمِّهِ ."
    },
    "en": {
      "narrator": "Abu Qatadah رضی اللہ عنہ reported:",
      "text": "The Messenger of Allah صلی ‌اللہ ‌علیہ ‌وسلم as saying: I stand up to pray and intend to prolong it; but when I hear the cry of a boy I shorten if for fear that his mother might be distressed."
    },
    "ur": {
      "narrator": "ہم سے عبدالرحمٰن بن ابراہیم نے بیان کیا، ہم سے عمر بن عبد الواحد اور بشر بن بکر نے بیان کیا، انہوں نے اوزاعی کی سند سے، یحییٰ بن ابی کثیر کی سند سے، انہوں نے عبداللہ بن ابوقتادہ رضی اللہ عنہ کہتے ہیں کہ",
      "text": "رسول اللہ صلی اللہ علیہ وسلم نے فرمایا: میں نماز کے لیے کھڑا ہوتا ہوں اور میں چاہتا ہوں کہ اسے لمبی کروں پھر میں بچے کے رونے کی آواز سنتا ہوں، تو اسے مختصر کر دیتا ہوں، اس اندیشہ سے کہ میں اس کی ماں کو مشقت میں نہ ڈال دوں ۔"
    },
    "al": {
      "text": ""
    }
  }
}