{
  "id": 800,
  "metadata": {
    "volume": {
      "id": 1
    },
    "chapter": {
      "id": 2,
      "language": {
        "en": {
          "text": "Prayer (Kitab Al-Salat)"
        },
        "ar": {
          "text": "كتاب الصلاة"
        },
        "ur": {
          "text": "نماز کے احکام و مسائل"
        },
        "al": {
          "text": ""
        }
      }
    }
  },
  "language": {
    "ar": {
      "text": "حَدَّثَنَا الْحَسَنُ بْنُ عَلِيٍّ، ‏‏‏‏‏‏حَدَّثَنَا عَبْدُ الرَّزَّاقِ، ‏‏‏‏‏‏أَخْبَرَنَا مَعْمَرٌ، ‏‏‏‏‏‏عَنْ يَحْيَى، ‏‏‏‏‏‏عَنْ عَبْدِ اللَّهِ بْنِ أَبِي قَتَادَةَ، ‏‏‏‏‏‏عَنْ أَبِيهِ، ‏‏‏‏‏‏قَالَ:‏‏‏‏ فَظَنَنَّا أَنَّهُ يُرِيدُ بِذَلِكَ أَنْ يُدْرِكَ النَّاسُ الرَّكْعَةَ الْأُولَى."
    },
    "en": {
      "narrator": "Abu Qatadah رضی اللہ عنہ said:",
      "text": "We thought that by this (prolonging the first rak’ah). He (the prophet) meant that the people might join the first rak’ah"
    },
    "ur": {
      "narrator": "ہم سے حسن بن علی نے بیان کیا، کہا ہم سے عبد الرزاق نے بیان کیا، کہا ہم سے معمر نے، یحییٰ کی سند سے، عبداللہ بن عبداللہ بن ابوقتادہ رضی اللہ عنہ کہتے ہیں کہ",
      "text": "ہمارا خیال ہے کہ آپ صلی اللہ علیہ وسلم ایسا اس لیے کرتے تھے کہ لوگ پہلی رکعت پا جائیں۔"
    },
    "al": {
      "text": ""
    }
  }
}