{
  "id": 4535,
  "metadata": {
    "volume": {
      "id": 5
    },
    "chapter": {
      "id": 33,
      "language": {
        "en": {
          "text": "The Book Of Jihad And Expeditions"
        },
        "ar": {
          "text": "كتاب الْجِهَادِ وَالسِّيَرِ"
        },
        "ur": {
          "text": "جہاد اور اس کے دوران میں رسول اللہ صلی اللہ علیہ وسلم کے اختیار کردہ طریقے"
        },
        "al": {
          "text": ""
        }
      }
    }
  },
  "language": {
    "ar": {
      "text": "وحَدَّثَنَا أَبُو بَكْرِ بْنُ أَبِي شَيْبَةَ، حَدَّثَنَا يَحْيَى بْنُ آدَمَ، عَنْ يَزِيدَ بْنِ عَبْدِ الْعَزِيزِ، عَنِ الْأَعْمَشِ، عَنْ شَقِيقٍ، عَنْ عَبْدِ اللهِ، قَالَ: قَالَ رَسُولُ اللهِ صَلَّى اللهُ عَلَيْهِ وَسَلَّمَ: لِكُلِّ غَادِرٍ لِوَاءٌ يَوْمَ الْقِيَامَةِ يُعْرَفُ بِهِ، يُقَالُ: هَذِهِ غَدْرَةُ فُلَانٍ."
    },
    "en": {
      "narrator": "It has been narrated on the authority of Abdullah رضی اللہ عنہ :",
      "text": "The Messenger of Allah ( ‌صلی ‌اللہ ‌علیہ ‌وسلم ‌) said: There will be for every perfidious person on the Day of Judgment a flag by which he will be recognized. It will be announced: Here is the breach of faith of so and so."
    },
    "ur": {
      "narrator": "ہم سے ابوبکر بن ابی شیبہ نے بیان کیا، کہا ہم سے یحییٰ بن آدم نے بیان کیا, یزید بن عبدالعزیز نے اعمش سے ، انہوں نے شقیق سے اور انہوں نے حضرت عبداللہ رضی اللہ عنہ سے روایت کی ، انہوں نے کہا",
      "text": "رسول اللہ صلی اللہ علیہ وسلم نے فرمایا : \" ہر عہد شکن کے لیے قیامت کے دن ایک جھنڈا ہو گا ، وہ اس کے ذریعے سے پہچانا جائے گا ، کہا جائے گا : یہ فلاں کی بدعہدی ( کا نشان ) ہے."
    },
    "al": {
      "text": ""
    }
  }
}