{
  "id": 2356,
  "metadata": {
    "volume": {
      "id": 3
    },
    "chapter": {
      "id": 15,
      "language": {
        "en": {
          "text": "The Chapter on Rulings"
        },
        "ar": {
          "text": "كتاب الأحكام"
        },
        "ur": {
          "text": "قضا کے احکام و مسائل"
        },
        "al": {
          "text": ""
        }
      }
    }
  },
  "language": {
    "ar": {
      "text": "حَدَّثَنَا أَبُو بَكْرِ بْنُ أَبِي شَيْبَةَ، ‏‏‏‏‏‏حَدَّثَنَا شَبَابَةُ، ‏‏‏‏‏‏حَدَّثَنَا اللَّيْثُ بْنُ سَعْدٍ، ‏‏‏‏‏‏عَنْ بُكَيْرِ بْنِ عَبْدِ اللَّهِ بْنِ الْأَشَجِّ، ‏‏‏‏‏‏عَنْ عِيَاضِ بْنِ عَبْدِ اللَّهِ بْنِ سَعْدٍ، ‏‏‏‏‏‏عَنْ أَبِي سَعِيدٍ الْخُدْرِيِّ، ‏‏‏‏‏‏قَالَ:‏‏‏‏ أُصِيبَ رَجُلٌ فِي عَهْدِ رَسُولِ اللَّهِ صَلَّى اللَّهُ عَلَيْهِ وَسَلَّمَ فِي ثِمَارٍ ابْتَاعَهَا فَكَثُرَ دَيْنُهُ، ‏‏‏‏‏‏فَقَالَ رَسُولُ اللَّهِ صَلَّى اللَّهُ عَلَيْهِ وَسَلَّمَ:‏‏‏‏ تَصَدَّقُوا عَلَيْهِ ، ‏‏‏‏‏‏فَتَصَدَّقَ النَّاسُ عَلَيْهِ فَلَمْ يَبْلُغْ ذَلِكَ وَفَاءَ دَيْنِهِ، ‏‏‏‏‏‏فَقَالَ رَسُولُ اللَّهِ صَلَّى اللَّهُ عَلَيْهِ وَسَلَّمَ:‏‏‏‏ خُذُوا مَا وَجَدْتُمْ وَلَيْسَ لَكُمْ إِلَّا ذَلِكَ يَعْنِي الْغُرَمَاءَ."
    },
    "en": {
      "narrator": "It was narrated that Abu Sa'eed Al-Khudri رضی اللہ عنہ said:",
      "text": "“At the time of the Messenger of Allah (ﷺ), a man suffered loss of some fruit that he had purchase, and his debts increased. The Messenger of Allah (ﷺ) said: 'Give him charity.' So the people gave him charity, but that was not enough to pay off his debts. The Messenger of Allah (ﷺ) said: “Take what you find, but you have no right to more than that, meaning his creditors.”"
    },
    "ur": {
      "narrator": "ہم سے ابوبکر بن ابی شیبہ نے بیان کیا، کہا: ہم سے شبابہ نے بیان کیا، کہا: ہم سے لیث بن سعد نے بیان کیا، ان سے بکر بن عبداللہ بن اشج نے بیان کیا، انہوں نے عیاض بن عبد اللہ بن سعد رضی اللہ عنہ سے, ابو سعید خدری رضی اللہ عنہ کہتے ہیں کہ",
      "text": "رسول اللہ صلی اللہ علیہ وسلم کے عہد میں ایک شخص کو اس کے خریدے ہوئے پھلوں میں گھاٹا ہوا، اور وہ بہت زیادہ مقروض ہو گیا، تو رسول اللہ صلی اللہ علیہ وسلم نے لوگوں سے فرمایا: تم لوگ اسے صدقہ دو چنانچہ لوگوں نے اسے صدقہ دیا، لیکن اس سے اس کا قرض پورا ادا نہ ہو سکا، بالآخر رسول اللہ صلی اللہ علیہ وسلم نے فرمایا: جو مل گیا وہ لے لو، اس کے علاوہ تمہارے لیے کچھ نہیں ہے یعنی قرض خواہوں کے لیے۔"
    },
    "al": {
      "text": ""
    }
  }
}