{
  "id": 2521,
  "metadata": {
    "volume": {
      "id": 3
    },
    "chapter": {
      "id": 23,
      "language": {
        "en": {
          "text": "The Book of Zakah"
        },
        "ar": {
          "text": "كتاب الزكاة"
        },
        "ur": {
          "text": "زکاۃ و صدقات کے احکام و مسائل"
        },
        "al": {
          "text": ""
        }
      }
    }
  },
  "language": {
    "ar": {
      "text": "أَخْبَرَنَا عَمْرُو بْنُ زُرَارَةَ، ‏‏‏‏‏‏قَالَ:‏‏‏‏ أَنْبَأَنَا الْقَاسِمُ وَهُوَ ابْنُ مَالِكٍ، ‏‏‏‏‏‏عَنِ الْجُعَيْدِ،‏‏‏‏ سَمِعْتُ السَّائِبَ بْنَ يَزِيدَ، ‏‏‏‏‏‏قَالَ:‏‏‏‏ كَانَ الصَّاعُ عَلَى عَهْدِ رَسُولِ اللَّهِ صَلَّى اللَّهُ عَلَيْهِ وَسَلَّمَ مُدًّا، ‏‏‏‏‏‏وَثُلُثًا بِمُدِّكُمُ الْيَوْمَ، ‏‏‏‏‏‏وَقَدْ زِيدَ فِيهِ ،‏‏‏‏ قَالَ أَبُو عَبْد الرَّحْمَنِ:‏‏‏‏ وحَدَّثَنِيهِ زِيَادُ بْنُ أَيُّوبَ."
    },
    "en": {
      "narrator": "",
      "text": "It was narrated from Al-Ju'aid: I heard As-Sa'ib bin Yazid say: 'During the time of Allah's messenger, the Sa' was equal to a Mudd and third of the Mudd you use today, and the Sa' of today has become large. ' (Sahih) Abu 'Abdur-Rahman (An-Nasa'i) said: And Ziyad bin Ayyub narrated it to me."
    },
    "ur": {
      "narrator": "سائب بن یزید رضی الله عنہ کہتے ہیں کہ",
      "text": "رسول اللہ صلی اللہ علیہ وسلم کے زمانہ میں ایک صاع تمہارے آج کے مد سے ایک مد اور ایک تہائی مد اور کچھ زائد کا تھا۔ اور ابوعبدالرحمٰن فرماتے ہیں: اس حدیث کو مجھ سے زیاد بن ایوب نے بیان کیا ہے۔"
    },
    "al": {
      "text": ""
    }
  }
}