{
  "id": 2627,
  "metadata": {
    "volume": {
      "id": 2
    },
    "chapter": {
      "id": 41,
      "language": {
        "en": {
          "text": "The Book on Faith"
        },
        "ar": {
          "text": "كتاب الإيمان عن رسول الله صلى الله عليه وسلم"
        },
        "ur": {
          "text": "ایمان و اسلام"
        },
        "al": {
          "text": ""
        }
      }
    }
  },
  "language": {
    "ar": {
      "text": "حَدَّثَنَا قُتَيْبَةُ، حَدَّثَنَا اللَّيْثُ، عَنِ ابْنِ عَجْلَانَ، عَنِ الْقَعْقَاعِ بْنِ حَكِيمٍ، عَنْ أَبِي صَالِحٍ، عَنْ أَبِي هُرَيْرَةَ، قَالَ:‏‏‏‏ قَالَ رَسُولُ اللَّهِ صَلَّى اللَّهُ عَلَيْهِ وَسَلَّمَ:‏‏‏‏ الْمُسْلِمُ مَنْ سَلِمَ الْمُسْلِمُونَ مِنْ لِسَانِهِ وَيَدِهِ، ‏‏‏‏‏‏وَالْمُؤْمِنُ مَنْ أَمِنَهُ النَّاسُ عَلَى دِمَائِهِمْ وَأَمْوَالِهِمْ ،‏‏‏‏ قَالَ أَبُو عِيسَى:‏‏‏‏ هَذَا حَدِيثٌ حَسَنٌ صَحِيحٌ. (حديث مرفوع) وَيُرْوَى عَنِ النَّبِيِّ صَلَّى اللَّهُ عَلَيْهِ وَسَلَّمَ، ‏‏‏‏‏‏أَنَّهُ سُئِلَ أَيُّ الْمُسْلِمِينَ أَفْضَلُ ؟ قَالَ:‏‏‏‏ مَنْ سَلِمَ الْمُسْلِمُونَ مِنْ لِسَانِهِ وَيَدِهِ ،‏‏‏‏ وفي الباب عن جَابِرٍ، ‏‏‏‏‏‏وَأَبِي مُوسَى، ‏‏‏‏‏‏وَعَبْدِ اللَّهِ بْنِ عَمْرٍو."
    },
    "en": {
      "narrator": "",
      "text": "Narrated Abu Hurairah: that the Messenger of Allah (ﷺ) said: The Muslim is the one from (the harm of) whose tongue and hand (other) Muslims are safe, and the believer is the one with whom the people trust their blood and their wealth."
    },
    "ur": {
      "narrator": "ابوہریرہ رضی الله عنہ کہتے ہیں کہ",
      "text": "رسول اللہ صلی اللہ علیہ وسلم نے فرمایا: ”مسلمان ( کامل ) وہ ہے جس کی زبان اور ہاتھ ( کے شر ) سے دوسرے مسلمان محفوظ رہیں، اور مومن ( کامل ) وہ ہے جس سے لوگ اپنی جانوں اور اپنے مالوں کو محفوظ سمجھیں“۔ امام ترمذی کہتے ہیں: ۱- یہ حدیث حسن صحیح ہے، ۲- اس باب میں جابر، ابوموسیٰ اور عبداللہ بن عمرو رضی الله عنہم سے ( بھی ) احادیث آئی ہیں، ۳- نبی اکرم صلی اللہ علیہ وسلم سے مروی ہے کہ آپ سے پوچھا گیا: سب سے بہتر مسلمان کون ہے؟ آپ نے فرمایا: ”جس کی زبان اور ہاتھ سے مسلمان محفوظ رہیں“۔"
    },
    "al": {
      "text": ""
    }
  }
}