{
  "id": 4073,
  "metadata": {
    "volume": {
      "id": 64
    },
    "chapter": {
      "id": 43,
      "language": {
        "en": {
          "text": "‘'Umra Al-Qada’"
        },
        "ar": {
          "text": "باب عُمْرَةُ الْقَضَاءِ"
        },
        "al": {
          "text": ""
        }
      }
    }
  },
  "language": {
    "ar": {
      "text": "حَدَّثَنَا عَلِيُّ بْنُ عَبْدِ اللَّهِ، حَدَّثَنَا سُفْيَانُ، عَنْ إِسْمَاعِيلَ بْنِ أَبِي خَالِدٍ، سَمِعَ ابْنَ أَبِي أَوْفَى، يَقُولُ لَمَّا اعْتَمَرَ رَسُولُ اللَّهِ صلى الله عليه وسلم سَتَرْنَاهُ مِنْ غِلْمَانِ الْمُشْرِكِينَ وَمِنْهُمْ، أَنْ يُؤْذُوا رَسُولَ اللَّهِ صلى الله عليه وسلم‏.‏"
    },
    "al": {
      "text": "Transmeton Ibn Ebi Aufa: Kur i Dërguari i Allahut (s.a.v.s.) kreu Umren (të cilën e kreu një vit pas marrëveshjes së Hudejbijes), ne e mbronim të Dërguarin e Allahut (s.a.v.s.) nga idhujtarët dhe fëmijët e tyre, në mënyrë që të mos e lëndonin atë."
    },
    "en": {
      "narrator": "Narrated Ibn Abi `Aufa:",
      "text": "When Allah's Messenger (ﷺ) performed the `Umra (which he performed in the year following the treaty of Al-Hudaibiya) we were screening Allah's Messenger (ﷺ) from the infidels and their boys lest they should harm him."
    }
  }
}