{
  "id": 66,
  "metadata": {
    "volume": {
      "id": 1
    },
    "chapter": {
      "id": 1,
      "language": {
        "en": {
          "text": "The Book of the Sunnah"
        },
        "ar": {
          "text": "كتاب السنة"
        },
        "ur": {
          "text": "سنت کی اہمیت وفضیلت"
        },
        "al": {
          "text": ""
        }
      }
    }
  },
  "language": {
    "ar": {
      "text": "حَدَّثَنَا مُحَمَّدُ بْنُ بَشَّارٍ، ‏‏‏‏‏‏ وَمُحَمَّدُ بْنُ الْمُثَنَّى، ‏‏‏‏‏‏قَالَا:‏‏‏‏ حَدَّثَنَا مُحَمَّدُ بْنُ جَعْفَرٍ، ‏‏‏‏‏‏حَدَّثَنَا شُعْبَةُ، ‏‏‏‏‏‏قَالَ:‏‏‏‏ سَمِعْتُ قَتَادَةَ يُحَدِّثُ، ‏‏‏‏‏‏عَنْ أَنَسِ بْنِ مَالِكٍ، ‏‏‏‏‏‏أَنَّ رَسُولَ اللَّهِ صَلَّى اللَّهُ عَلَيْهِ وَسَلَّمَ قَالَ:‏‏‏‏ لَا يُؤْمِنُ أَحَدُكُمْ حَتَّى يُحِبَّ لِأَخِيهِ، ‏‏‏‏‏‏أَوْ قَالَ:‏‏‏‏ لِجَارِهِ مَا يُحِبُّ لِنَفْسِهِ ."
    },
    "en": {
      "narrator": "It was narrated from Anas bin Malik رضی اللہ عنہ :",
      "text": "The Messenger of Allah (ﷺ) said: 'None of you truly believes until he loves for his brother or he said for his neighbor, what he loves for himself."
    },
    "ur": {
      "narrator": "ہم سے محمد بن بشار اور محمد بن المثنی نے بیان کیا، کہا ہم سے محمد بن جعفر نے بیان کیا، کہا کہ ہم سے شعبہ نے بیان کیا کہ میں نے قتادہ کو بیان کرتے ہوئے سنا, انس بن مالک رضی اللہ عنہ کہتے ہیں کہ",
      "text": "رسول اللہ صلی اللہ علیہ وسلم نے فرمایا: کوئی شخص مومن نہیں ہو سکتا جب تک کہ وہ اپنے بھائی ( یا اپنے پڑوسی ) کے لیے وہی چیز پسند نہ کرے جو وہ اپنے لیے پسند کرتا ہے ۔"
    },
    "al": {
      "text": ""
    }
  }
}