{
  "id": 5850,
  "metadata": {
    "volume": {
      "id": 78
    },
    "chapter": {
      "id": 66,
      "language": {
        "en": {
          "text": "Whoever spruced himself up for the delegates."
        },
        "ar": {
          "text": "باب مَنْ تَجَمَّلَ لِلْوُفُودِ"
        },
        "al": {
          "text": ""
        }
      }
    }
  },
  "language": {
    "ar": {
      "text": "حَدَّثَنَا عَبْدُ اللَّهِ بْنُ مُحَمَّدٍ، حَدَّثَنَا عَبْدُ الصَّمَدِ، قَالَ حَدَّثَنِي أَبِي قَالَ، حَدَّثَنِي يَحْيَى بْنُ أَبِي إِسْحَاقَ، قَالَ قَالَ لِي سَالِمُ بْنُ عَبْدِ اللَّهِ مَا الإِسْتَبْرَقُ قُلْتُ مَا غَلُظَ مِنَ الدِّيبَاجِ وَخَشُنَ مِنْهُ‏.‏ قَالَ سَمِعْتُ عَبْدَ اللَّهِ يَقُولُ رَأَى عُمَرُ عَلَى رَجُلٍ حُلَّةً مِنْ إِسْتَبْرَقٍ فَأَتَى بِهَا النَّبِيَّ صلى الله عليه وسلم فَقَالَ يَا رَسُولَ اللَّهِ اشْتَرِ هَذِهِ فَالْبَسْهَا لِوَفْدِ النَّاسِ إِذَا قَدِمُوا عَلَيْكَ‏.‏ فَقَالَ ‏\"‏ إِنَّمَا يَلْبَسُ الْحَرِيرَ مَنْ لاَ خَلاَقَ لَهُ ‏\"‏‏.‏ فَمَضَى فِي ذَلِكَ مَا مَضَى، ثُمَّ إِنَّ النَّبِيَّ صلى الله عليه وسلم بَعَثَ إِلَيْهِ بِحُلَّةٍ فَأَتَى بِهَا النَّبِيَّ صلى الله عليه وسلم فَقَالَ بَعَثْتَ إِلَىَّ بِهَذِهِ، وَقَدْ قُلْتَ فِي مِثْلِهَا مَا قُلْتَ قَالَ ‏\"‏ إِنَّمَا بَعَثْتُ إِلَيْكَ لِتُصِيبَ بِهَا مَالاً ‏\"‏‏.‏ فَكَانَ ابْنُ عُمَرَ يَكْرَهُ الْعَلَمَ فِي الثَّوْبِ لِهَذَا الْحَدِيثِ‏.‏"
    },
    "al": {
      "text": "Transmeton Abdullah ibn Omeri: Omeri pa një rrobë prej mëndafshi (istabrak) te një burrë, prandaj e solli te Pejgamberi (s.a.v.s.) dhe i tha: \"O i Dërguari i Allahut! Bleje këtë dhe vishe kur të vijnë delegacionet te ti.\" Ai tha: \"Mëndafshin e vesh vetëm ai që nuk ka pjesë në botën tjetër.\" Pas një kohe, Pejgamberi (s.a.v.s.) i dërgoi Omerit një rrobë të tillë. Omeri e solli atë te Pejgamberi (s.a.v.s.) dhe i tha: \"Ma dërgove këtë, ndërkohë që më parë ke thënë atë që ke thënë për të?\" Pejgamberi (s.a.v.s.) i tha: \"Ta dërgova që të nxjerrësh fitim prej saj.\" Për këtë arsye, Ibn Omeri i urrente qëndisjet prej mëndafshi në rroba."
    },
    "en": {
      "narrator": "Narrated `Abdullah:",
      "text": "`Umar saw a silken cloak over a man (for sale) so he took it to the Prophet (ﷺ) and said, 'O Allah's Apostle! Buy this and wear it when the delegate come to you.' He said, 'The silk is worn by one who will have no share (in the Here-after).' Some time passed after this event, and then the Prophet (ﷺ) sent a (similar) cloak to him. `Umar brought that cloak back to the Prophet (ﷺ) and said, 'You have sent this to me, and you said about a similar one what you said?' The Prophet (ﷺ) said, 'I have sent it to you so that you may get money by selling it.' Because of this, Ibn `Umar used to hate the silken markings on the garments."
    }
  }
}