{
  "id": 1375,
  "metadata": {
    "volume": {
      "id": 1
    },
    "chapter": {
      "id": 4,
      "language": {
        "en": {
          "text": "Prayer"
        },
        "ar": {
          "text": "كتاب الصلاة"
        },
        "ur": {
          "text": "نماز کا بیان"
        },
        "al": {
          "text": ""
        }
      }
    }
  },
  "language": {
    "ar": {
      "text": "وَعَنْ عَبْدِ اللَّهِ بْنِ عَمْرٍو عَنِ النَّبِيِّ صلى الله عَلَيْهِ وَسلم: «الْجُمُعَةُ عَلَى مَنْ سَمِعَ النِّدَاءَ» . رَوَاهُ أَبُو دَاوُد"
    },
    "en": {
      "narrator": "",
      "text": ""
    },
    "ur": {
      "narrator": "",
      "text": "عبداللہ بن عمرو ؓ نبی صلی ‌اللہ ‌علیہ ‌وآلہ ‌وسلم سے بیان کرتے ہیں ، آپ نے فرمایا :’’ جو شخص اذان سنے اس پر جمعہ فرض ہے ۔‘‘ ضعیف ۔"
    },
    "al": {
      "text": ""
    }
  }
}