{
  "id": 3812,
  "metadata": {
    "volume": {
      "id": 5
    },
    "chapter": {
      "id": 35,
      "language": {
        "en": {
          "text": "Etiquette"
        },
        "ar": {
          "text": "كتاب الأدب"
        },
        "ur": {
          "text": "آداب و اخلاق"
        },
        "al": {
          "text": ""
        }
      }
    }
  },
  "language": {
    "ar": {
      "text": "حَدَّثَنَا نَصْرُ بْنُ عَبْدِ الرَّحْمَنِ الْوَشَّاءُ،‏‏‏‏ حَدَّثَنَا عَبْدُ الرَّحْمَنِ الْمُحَارِبِيُّ،‏‏‏‏ عَنْ مَالِكِ بْنِ أَنَسٍ،‏‏‏‏ عَنْ سُمَيٍّ،‏‏‏‏ عَنْ أَبِي صَالِحٍ،‏‏‏‏ عَنْ أَبِي هُرَيْرَةَ،‏‏‏‏ قَالَ:‏‏‏‏ قَالَ رَسُولُ اللَّهِ صَلَّى اللَّهُ عَلَيْهِ وَسَلَّمَ:‏‏‏‏ مَنْ قَالَ:‏‏‏‏ سُبْحَانَ اللَّهِ وَبِحَمْدِهِ مِائَةَ مَرَّةٍ،‏‏‏‏ غُفِرَتْ لَهُ ذُنُوبُهُ وَلَوْ كَانَتْ مِثْلَ زَبَدِ الْبَحْرِ ."
    },
    "en": {
      "narrator": "It was narrated from Abu Hurairah رضی اللہ عنہ that:",
      "text": "The Messenger of Allah (ﷺ) said: Whoever says: Subhan Allahi wa bi hamdihi (Glory and praise is to Allah) one hundred times, his sins will be forgiven even if they were like the foam of the sea.'"
    },
    "ur": {
      "narrator": "ہم سے نصر بن عبدالرحمٰن الوشاع نے بیان کیا، ہم سے عبدالرحمٰن المحربی نے، مالک بن انس سے، سمیہ کی سند سے، ابو صالح کی سند سے, ابوہریرہ رضی اللہ عنہ کہتے ہیں کہ",
      "text": "رسول اللہ صلی اللہ علیہ وسلم نے فرمایا: جو شخص سو بار «سبحان الله وبحمده» کہے تو اس کے گناہ معاف کر دئیے جائیں گے، اگرچہ سمندر کے جھاگ کے برابر ہی کیوں نہ ہوں ۔"
    },
    "al": {
      "text": ""
    }
  }
}