{
  "id": 4274,
  "metadata": {
    "volume": {
      "id": 4
    },
    "chapter": {
      "id": 28,
      "language": {
        "en": {
          "text": "The Book Of Oaths"
        },
        "ar": {
          "text": "كتاب الْأَيْمَانِ"
        },
        "ur": {
          "text": "قسموں کا بیان"
        },
        "al": {
          "text": ""
        }
      }
    }
  },
  "language": {
    "ar": {
      "text": "وحَدَّثَنِي الْقَاسِمُ بْنُ زَكَرِيَّا، حَدَّثَنَا خَالِدُ بْنُ مَخْلَدٍ، حَدَّثَنِي سُلَيْمَانُ يَعْنِي ابْنَ بِلَالٍ، حَدَّثَنِي سُهَيْلٌ، فِي هَذَا الْإِسْنَادِ بِمَعْنَى حَدِيثِ مَالِكٍ: «فَلْيُكَفِّرْ يَمِينَهُ، وَلْيَفْعَلِ الَّذِي هُوَ خَيْرٌ."
    },
    "en": {
      "narrator": "This hadith is narrated on the authority of Suhail with the same chain of transmitters (with these words):",
      "text": "He should expiate for (breaking) the vow and do that which is better."
    },
    "ur": {
      "narrator": "مجھ سے القاسم بن زکریا نے بیان کیا، کہا ہم سے خالد بن مخلد نے بیان کیا,سلیمان بن بلال نے مجھے سہیل سے اسی سند کے ساتھ امام مالک کی حدیث کے ہم معنی حدیث ( ان الفاظ میں ) بیان کی",
      "text": "\" اسے چاہئے کہ اپنی قسم کا کفارہ دے اور وہ کام کرے جو بہتر ہے."
    },
    "al": {
      "text": ""
    }
  }
}